pypeek/.DS_Store
pypeek/__init__.py
pypeek/__main__.py
pypeek/ffmpeg.py
pypeek/main.py
pypeek/qrangeslider.py
pypeek/shortcut.py
pypeek/undo.py
pypeek/icon/arrow-up-right.png
pypeek/icon/arrows-angle-expand.png
pypeek/icon/bounding-box-circles.png
pypeek/icon/broom.png
pypeek/icon/camera.png
pypeek/icon/caret-down-fill.png
pypeek/icon/circle.png
pypeek/icon/crop.png
pypeek/icon/cursor-light.png
pypeek/icon/cursor.png
pypeek/icon/display.png
pypeek/icon/eyedropper.png
pypeek/icon/filled-circle.png
pypeek/icon/filled-square.png
pypeek/icon/fonts.png
pypeek/icon/gear-fill.png
pypeek/icon/gear.png
pypeek/icon/in-progress.png
pypeek/icon/line-width.png
pypeek/icon/move.png
pypeek/icon/palette.png
pypeek/icon/pause.png
pypeek/icon/peek-recording.png
pypeek/icon/peek.icns
pypeek/icon/peek.ico
pypeek/icon/peek.png
pypeek/icon/pencil.png
pypeek/icon/play-fill.png
pypeek/icon/record-fill.png
pypeek/icon/slash-lg.png
pypeek/icon/square.png
pypeek/icon/stop-fill copy.png
pypeek/icon/stop-fill.png
pypeek/icon/video-camera.png
pypeek/icon/window.png
pypeek/icon/x.png
pypeek/icon/zoom-in.png
pypeek/icon/zoom-out.png
pypeek/icon/zoom-reset.png
pypeek-2.10.11.dist-info/METADATA
pypeek-2.10.11.dist-info/WHEEL
pypeek-2.10.11.dist-info/entry_points.txt
pypeek-2.10.11.dist-info/licenses/LICENSE
pypeek-2.10.11.dist-info/RECORD
