Metadata-Version: 2.1
Name: pypeek
Version: 2.10.11
Summary: An animated GIF recorder
Project-URL: Homepage, https://github.com/firatkiral/pypeek
Project-URL: Bug Tracker, https://github.com/firatkiral/pypeek/issues
Author-email: Firat Kiral <firatkiral@gmail.com>
License-File: LICENSE
Keywords: animation,capture,gif,mp4,record,recorder,screen,screenshot,video,webm
Classifier: License :: OSI Approved :: GNU General Public License v3 (GPLv3)
Classifier: Operating System :: OS Independent
Classifier: Programming Language :: Python :: 3
Requires-Python: >=3.9
Requires-Dist: pyside6>=6.4.0
Requires-Dist: requests>=2.31.0
